tbump/__init__.py
tbump/__main__.py
tbump/action.py
tbump/cli.py
tbump/config.py
tbump/error.py
tbump/executor.py
tbump/file_bumper.py
tbump/git.py
tbump/git_bumper.py
tbump/hooks.py
tbump/init.py
tbump/py.typed
tbump/test/__init__.py
tbump/test/conftest.py
tbump/test/project/VERSION
tbump/test/project/after.py
tbump/test/project/before.py
tbump/test/project/glob-one.c
tbump/test/project/glob-two.v
tbump/test/project/package.json
tbump/test/project/pub.js
tbump/test/project/tbump.toml
tbump/test/project/version_info.py
tbump/test/project/yarn.lock
tbump/test/pyproject/README.rst
tbump/test/pyproject/foo/__init__.py
tbump/test/pyproject/pyproject.toml
tbump/test/test_api.py
tbump/test/test_cli.py
tbump/test/test_config.py
tbump/test/test_file_bumper.py
tbump/test/test_git_bumper.py
tbump/test/test_hooks.py
tbump/test/test_init.py
tbump-6.10.0.dist-info/LICENSE
tbump-6.10.0.dist-info/METADATA
tbump-6.10.0.dist-info/WHEEL
tbump-6.10.0.dist-info/entry_points.txt
tbump-6.10.0.dist-info/RECORD
