Metadata-Version: 2.1
Name: tbump
Version: 6.10.0
Summary: Bump software releases
Home-page: https://github.com/dmerejkowsky/tbump
License: BSD-3-Clause
Author: Dimitri Merejkowsky
Author-email: dimitri@dmerej.info
Requires-Python: >=3.7,<4.0
Classifier: License :: OSI Approved :: BSD License
Classifier: Programming Language :: Python :: 3
Classifier: Programming Language :: Python :: 3.7
Classifier: Programming Language :: Python :: 3.8
Classifier: Programming Language :: Python :: 3.9
Classifier: Programming Language :: Python :: 3.10
Classifier: Programming Language :: Python :: 3.11
Requires-Dist: cli-ui (>=0.10.3)
Requires-Dist: docopt (>=0.6.2,<0.7.0)
Requires-Dist: schema (>=0.7.1,<0.8.0)
Requires-Dist: tomlkit (>=0.11,<0.12)
Project-URL: Changelog, https://github.com/dmerejkowsky/tbump/blob/main/Changelog.rst
Project-URL: Issues, https://github.com/dmerejkowsky/tbump/issues
Project-URL: Repository, https://github.com/dmerejkowsky/tbump
